{
    "__inputs": [
        {
            "name": "DS_PROMETHEUS",
            "label": "Prometheus",
            "description": "",
            "type": "datasource",
            "pluginId": "prometheus",
            "pluginName": "Prometheus"
        }
    ],
    "__elements": {},
    "__requires": [
        {
            "type": "grafana",
            "id": "grafana",
            "name": "Grafana",
            "version": "10.4.2"
        },
        {
            "type": "datasource",
            "id": "prometheus",
            "name": "Prometheus",
            "version": "1.0.0"
        },
        {
            "type": "panel",
            "id": "stat",
            "name": "Stat",
            "version": ""
        },
        {
            "type": "panel",
            "id": "timeseries",
            "name": "Time series",
            "version": ""
        }
    ],
    "annotations": {
        "list": [
            {
                "builtIn": 1,
                "datasource": {
                    "type": "grafana",
                    "uid": "-- Grafana --"
                },
                "enable": true,
                "hide": true,
                "iconColor": "rgba(0, 211, 255, 1)",
                "name": "Annotations & Alerts",
                "target": {
                    "limit": 100,
                    "matchAny": false,
                    "tags": [],
                    "type": "dashboard"
                },
                "type": "dashboard"
            }
        ]
    },
    "editable": true,
    "fiscalYearStartMonth": 0,
    "graphTooltip": 0,
    "id": null,
    "links": [],
    "liveNow": false,
    "panels": [
        {
            "collapsed": false,
            "gridPos": {
                "h": 1,
                "w": 24,
                "x": 0,
                "y": 0
            },
            "id": 25,
            "panels": [],
            "title": "Aleo",
            "type": "row"
        },
        {
            "datasource": {
                "type": "prometheus",
                "uid": "${DS_PROMETHEUS}"
            },
            "fieldConfig": {
                "defaults": {
                    "color": {
                        "mode": "thresholds"
                    },
                    "mappings": [],
                    "thresholds": {
                        "mode": "absolute",
                        "steps": [
                            {
                                "color": "green",
                                "value": null
                            }
                        ]
                    }
                },
                "overrides": []
            },
            "gridPos": {
                "h": 4,
                "w": 4,
                "x": 0,
                "y": 1
            },
            "id": 32,
            "options": {
                "colorMode": "value",
                "graphMode": "area",
                "justifyMode": "auto",
                "orientation": "auto",
                "reduceOptions": {
                    "calcs": [
                        "lastNotNull"
                    ],
                    "fields": "",
                    "values": false
                },
                "showPercentChange": false,
                "textMode": "auto",
                "wideLayout": true
            },
            "pluginVersion": "10.4.2",
            "targets": [
                {
                    "datasource": {
                        "type": "prometheus",
                        "uid": "${DS_PROMETHEUS}"
                    },
                    "disableTextWrap": false,
                    "editorMode": "builder",
                    "expr": "max(snarkos_bft_height_total{chain=\"$chain\"})",
                    "fullMetaSearch": false,
                    "includeNullMetadata": true,
                    "instant": false,
                    "legendFormat": "__auto",
                    "range": true,
                    "refId": "A",
                    "useBackend": false
                }
            ],
            "title": "Block Height",
            "type": "stat"
        },
        {
            "datasource": {
                "type": "prometheus",
                "uid": "${DS_PROMETHEUS}"
            },
            "fieldConfig": {
                "defaults": {
                    "color": {
                        "mode": "thresholds"
                    },
                    "mappings": [],
                    "thresholds": {
                        "mode": "absolute",
                        "steps": [
                            {
                                "color": "green",
                                "value": null
                            }
                        ]
                    }
                },
                "overrides": []
            },
            "gridPos": {
                "h": 4,
                "w": 4,
                "x": 4,
                "y": 1
            },
            "id": 6,
            "options": {
                "colorMode": "value",
                "graphMode": "area",
                "justifyMode": "auto",
                "orientation": "auto",
                "reduceOptions": {
                    "calcs": [
                        "lastNotNull"
                    ],
                    "fields": "",
                    "values": false
                },
                "showPercentChange": false,
                "textMode": "auto",
                "wideLayout": true
            },
            "pluginVersion": "10.4.2",
            "targets": [
                {
                    "datasource": {
                        "type": "prometheus",
                        "uid": "${DS_PROMETHEUS}"
                    },
                    "disableTextWrap": false,
                    "editorMode": "code",
                    "expr": "snarkos_bft_primary_proposal_round{role=\"validator\",chain=\"$chain\"}",
                    "fullMetaSearch": false,
                    "includeNullMetadata": true,
                    "legendFormat": "__auto",
                    "range": true,
                    "refId": "A",
                    "useBackend": false
                }
            ],
            "title": "Proposal Round",
            "type": "stat"
        },
        {
            "datasource": {
                "type": "prometheus",
                "uid": "${DS_PROMETHEUS}"
            },
            "fieldConfig": {
                "defaults": {
                    "color": {
                        "mode": "thresholds"
                    },
                    "mappings": [],
                    "thresholds": {
                        "mode": "absolute",
                        "steps": [
                            {
                                "color": "green",
                                "value": null
                            }
                        ]
                    }
                },
                "overrides": []
            },
            "gridPos": {
                "h": 4,
                "w": 4,
                "x": 8,
                "y": 1
            },
            "id": 8,
            "options": {
                "colorMode": "value",
                "graphMode": "area",
                "justifyMode": "auto",
                "orientation": "auto",
                "reduceOptions": {
                    "calcs": [
                        "lastNotNull"
                    ],
                    "fields": "",
                    "values": false
                },
                "showPercentChange": false,
                "textMode": "auto",
                "wideLayout": true
            },
            "pluginVersion": "10.4.2",
            "targets": [
                {
                    "datasource": {
                        "type": "prometheus",
                        "uid": "${DS_PROMETHEUS}"
                    },
                    "disableTextWrap": false,
                    "editorMode": "code",
                    "expr": "snarkos_blocks_coinbase_target{role=\"validator\",chain=\"$chain\"}",
                    "fullMetaSearch": false,
                    "includeNullMetadata": true,
                    "legendFormat": "__auto",
                    "range": true,
                    "refId": "A",
                    "useBackend": false
                }
            ],
            "title": "Coinbase Target",
            "type": "stat"
        },
        {
            "datasource": {
                "type": "prometheus",
                "uid": "${DS_PROMETHEUS}"
            },
            "fieldConfig": {
                "defaults": {
                    "color": {
                        "mode": "thresholds"
                    },
                    "mappings": [],
                    "thresholds": {
                        "mode": "absolute",
                        "steps": [
                            {
                                "color": "green",
                                "value": null
                            }
                        ]
                    }
                },
                "overrides": []
            },
            "gridPos": {
                "h": 4,
                "w": 4,
                "x": 12,
                "y": 1
            },
            "id": 11,
            "options": {
                "colorMode": "value",
                "graphMode": "area",
                "justifyMode": "auto",
                "orientation": "auto",
                "reduceOptions": {
                    "calcs": [
                        "lastNotNull"
                    ],
                    "fields": "",
                    "values": false
                },
                "showPercentChange": false,
                "textMode": "auto",
                "wideLayout": true
            },
            "pluginVersion": "10.4.2",
            "targets": [
                {
                    "datasource": {
                        "type": "prometheus",
                        "uid": "${DS_PROMETHEUS}"
                    },
                    "disableTextWrap": false,
                    "editorMode": "code",
                    "expr": "snarkos_blocks_proof_target{role=\"validator\",chain=\"$chain\"}",
                    "fullMetaSearch": false,
                    "includeNullMetadata": true,
                    "instant": false,
                    "legendFormat": "__auto",
                    "range": true,
                    "refId": "A",
                    "useBackend": false
                }
            ],
            "title": "Proof Target",
            "type": "stat"
        },
        {
            "datasource": {
                "type": "prometheus",
                "uid": "${DS_PROMETHEUS}"
            },
            "fieldConfig": {
                "defaults": {
                    "color": {
                        "mode": "thresholds"
                    },
                    "mappings": [],
                    "thresholds": {
                        "mode": "absolute",
                        "steps": [
                            {
                                "color": "green",
                                "value": null
                            },
                            {
                                "color": "red",
                                "value": 80
                            }
                        ]
                    }
                },
                "overrides": []
            },
            "gridPos": {
                "h": 4,
                "w": 4,
                "x": 16,
                "y": 1
            },
            "id": 24,
            "options": {
                "colorMode": "value",
                "graphMode": "area",
                "justifyMode": "auto",
                "orientation": "auto",
                "reduceOptions": {
                    "calcs": [
                        "lastNotNull"
                    ],
                    "fields": "",
                    "values": false
                },
                "showPercentChange": false,
                "textMode": "auto",
                "wideLayout": true
            },
            "pluginVersion": "10.4.2",
            "targets": [
                {
                    "datasource": {
                        "type": "prometheus",
                        "uid": "${DS_PROMETHEUS}"
                    },
                    "disableTextWrap": false,
                    "editorMode": "code",
                    "expr": "snarkos_consensus_committed_certificates_total{role=\"validator\",chain=\"$chain\"}",
                    "fullMetaSearch": false,
                    "includeNullMetadata": true,
                    "instant": false,
                    "legendFormat": "__auto",
                    "range": true,
                    "refId": "A",
                    "useBackend": false
                }
            ],
            "title": "Committed Certificates",
            "type": "stat"
        },
        {
            "datasource": {
                "type": "prometheus",
                "uid": "${DS_PROMETHEUS}"
            },
            "fieldConfig": {
                "defaults": {
                    "color": {
                        "mode": "thresholds"
                    },
                    "mappings": [],
                    "thresholds": {
                        "mode": "absolute",
                        "steps": [
                            {
                                "color": "green",
                                "value": null
                            }
                        ]
                    }
                },
                "overrides": []
            },
            "gridPos": {
                "h": 4,
                "w": 4,
                "x": 20,
                "y": 1
            },
            "id": 26,
            "options": {
                "colorMode": "value",
                "graphMode": "area",
                "justifyMode": "auto",
                "orientation": "auto",
                "reduceOptions": {
                    "calcs": [
                        "lastNotNull"
                    ],
                    "fields": "",
                    "values": false
                },
                "showPercentChange": false,
                "textMode": "auto",
                "wideLayout": true
            },
            "pluginVersion": "10.4.2",
            "targets": [
                {
                    "datasource": {
                        "type": "prometheus",
                        "uid": "${DS_PROMETHEUS}"
                    },
                    "disableTextWrap": false,
                    "editorMode": "code",
                    "expr": "snarkos_bft_leaders_elected_total{role=\"validator\",chain=\"$chain\"}",
                    "fullMetaSearch": false,
                    "includeNullMetadata": true,
                    "legendFormat": "__auto",
                    "range": true,
                    "refId": "A",
                    "useBackend": false
                }
            ],
            "title": "Elected Leaders",
            "type": "stat"
        },
        {
            "datasource": {
                "type": "prometheus",
                "uid": "${DS_PROMETHEUS}"
            },
            "fieldConfig": {
                "defaults": {
                    "color": {
                        "mode": "thresholds"
                    },
                    "mappings": [],
                    "thresholds": {
                        "mode": "absolute",
                        "steps": [
                            {
                                "color": "green",
                                "value": null
                            },
                            {
                                "color": "green",
                                "value": 0
                            }
                        ]
                    }
                },
                "overrides": []
            },
            "gridPos": {
                "h": 4,
                "w": 4,
                "x": 0,
                "y": 5
            },
            "id": 12,
            "options": {
                "colorMode": "value",
                "graphMode": "area",
                "justifyMode": "auto",
                "orientation": "auto",
                "reduceOptions": {
                    "calcs": [
                        "lastNotNull"
                    ],
                    "fields": "",
                    "values": false
                },
                "showPercentChange": false,
                "textMode": "auto",
                "wideLayout": true
            },
            "pluginVersion": "10.4.2",
            "targets": [
                {
                    "datasource": {
                        "type": "prometheus",
                        "uid": "${DS_PROMETHEUS}"
                    },
                    "disableTextWrap": false,
                    "editorMode": "code",
                    "expr": "snarkvm_ledger_committee_total_stake{role=\"validator\",chain=\"$chain\"}",
                    "fullMetaSearch": false,
                    "includeNullMetadata": true,
                    "instant": false,
                    "legendFormat": "__auto",
                    "range": true,
                    "refId": "A",
                    "useBackend": false
                }
            ],
            "title": "Total Stake",
            "type": "stat"
        },
        {
            "datasource": {
                "type": "prometheus",
                "uid": "${DS_PROMETHEUS}"
            },
            "fieldConfig": {
                "defaults": {
                    "color": {
                        "mode": "thresholds"
                    },
                    "mappings": [],
                    "thresholds": {
                        "mode": "absolute",
                        "steps": [
                            {
                                "color": "green",
                                "value": null
                            }
                        ]
                    }
                },
                "overrides": []
            },
            "gridPos": {
                "h": 4,
                "w": 4,
                "x": 4,
                "y": 5
            },
            "id": 33,
            "options": {
                "colorMode": "value",
                "graphMode": "area",
                "justifyMode": "auto",
                "orientation": "auto",
                "reduceOptions": {
                    "calcs": [
                        "lastNotNull"
                    ],
                    "fields": "",
                    "values": false
                },
                "showPercentChange": false,
                "textMode": "auto",
                "wideLayout": true
            },
            "pluginVersion": "10.4.2",
            "targets": [
                {
                    "datasource": {
                        "type": "prometheus",
                        "uid": "${DS_PROMETHEUS}"
                    },
                    "disableTextWrap": false,
                    "editorMode": "code",
                    "expr": "max(snarkos_blocks_solutions_total{chain=\"$chain\"})",
                    "fullMetaSearch": false,
                    "includeNullMetadata": true,
                    "instant": false,
                    "legendFormat": "__auto",
                    "range": true,
                    "refId": "A",
                    "useBackend": false
                }
            ],
            "title": "Block Solutions",
            "type": "stat"
        },
        {
            "datasource": {
                "type": "prometheus",
                "uid": "${DS_PROMETHEUS}"
            },
            "fieldConfig": {
                "defaults": {
                    "color": {
                        "mode": "thresholds"
                    },
                    "displayName": "TPS averaged over 5 minutes",
                    "mappings": [],
                    "thresholds": {
                        "mode": "absolute",
                        "steps": [
                            {
                                "color": "green",
                                "value": null
                            }
                        ]
                    }
                },
                "overrides": []
            },
            "gridPos": {
                "h": 4,
                "w": 4,
                "x": 8,
                "y": 5
            },
            "id": 22,
            "options": {
                "colorMode": "value",
                "graphMode": "area",
                "justifyMode": "auto",
                "orientation": "auto",
                "reduceOptions": {
                    "calcs": [
                        "lastNotNull"
                    ],
                    "fields": "",
                    "values": false
                },
                "showPercentChange": false,
                "textMode": "auto",
                "wideLayout": true
            },
            "pluginVersion": "10.4.2",
            "targets": [
                {
                    "datasource": {
                        "type": "prometheus",
                        "uid": "${DS_PROMETHEUS}"
                    },
                    "disableTextWrap": false,
                    "editorMode": "builder",
                    "expr": "sum(rate(snarkos_blocks_transactions_total{chain=\"$chain\"}[5m]))",
                    "fullMetaSearch": false,
                    "includeNullMetadata": true,
                    "legendFormat": "__auto",
                    "range": true,
                    "refId": "A",
                    "useBackend": false
                }
            ],
            "title": "TPS",
            "type": "stat"
        },
        {
            "collapsed": false,
            "gridPos": {
                "h": 1,
                "w": 24,
                "x": 0,
                "y": 9
            },
            "id": 21,
            "panels": [],
            "title": "Node Health",
            "type": "row"
        },
        {
            "datasource": {
                "type": "prometheus",
                "uid": "${DS_PROMETHEUS}"
            },
            "fieldConfig": {
                "defaults": {
                    "color": {
                        "mode": "thresholds"
                    },
                    "mappings": [
                        {
                            "options": {
                                "0": {
                                    "color": "red",
                                    "index": 0,
                                    "text": "No"
                                }
                            },
                            "type": "value"
                        },
                        {
                            "options": {
                                "from": 1,
                                "result": {
                                    "color": "green",
                                    "index": 1,
                                    "text": "Yes"
                                },
                                "to": 1000000
                            },
                            "type": "range"
                        }
                    ],
                    "thresholds": {
                        "mode": "absolute",
                        "steps": [
                            {
                                "color": "green",
                                "value": null
                            }
                        ]
                    }
                },
                "overrides": []
            },
            "gridPos": {
                "h": 4,
                "w": 3,
                "x": 0,
                "y": 10
            },
            "id": 14,
            "options": {
                "colorMode": "background",
                "graphMode": "area",
                "justifyMode": "auto",
                "orientation": "auto",
                "reduceOptions": {
                    "calcs": [
                        "lastNotNull"
                    ],
                    "fields": "",
                    "values": false
                },
                "showPercentChange": false,
                "textMode": "auto",
                "wideLayout": true
            },
            "pluginVersion": "10.4.2",
            "targets": [
                {
                    "datasource": {
                        "type": "prometheus",
                        "uid": "${DS_PROMETHEUS}"
                    },
                    "disableTextWrap": false,
                    "editorMode": "code",
                    "exemplar": false,
                    "expr": "increase(snarkos_bft_height_total{role=\"validator\",chain=\"$chain\"}[5m]) > bool 1",
                    "format": "time_series",
                    "fullMetaSearch": false,
                    "includeNullMetadata": true,
                    "instant": false,
                    "legendFormat": "",
                    "range": true,
                    "refId": "A",
                    "useBackend": false
                }
            ],
            "title": "Validator Height Increasing?",
            "type": "stat"
        },
        {
            "datasource": {
                "type": "prometheus",
                "uid": "${DS_PROMETHEUS}"
            },
            "fieldConfig": {
                "defaults": {
                    "color": {
                        "mode": "thresholds"
                    },
                    "mappings": [],
                    "thresholds": {
                        "mode": "absolute",
                        "steps": [
                            {
                                "color": "green",
                                "value": null
                            }
                        ]
                    }
                },
                "overrides": []
            },
            "gridPos": {
                "h": 4,
                "w": 4,
                "x": 3,
                "y": 10
            },
            "id": 13,
            "options": {
                "colorMode": "value",
                "graphMode": "area",
                "justifyMode": "auto",
                "orientation": "auto",
                "reduceOptions": {
                    "calcs": [
                        "lastNotNull"
                    ],
                    "fields": "",
                    "values": false
                },
                "showPercentChange": false,
                "textMode": "auto",
                "wideLayout": true
            },
            "pluginVersion": "10.4.2",
            "targets": [
                {
                    "datasource": {
                        "type": "prometheus",
                        "uid": "${DS_PROMETHEUS}"
                    },
                    "disableTextWrap": false,
                    "editorMode": "code",
                    "expr": "snarkos_bft_height_total{role=\"validator\",chain=\"$chain\"}",
                    "fullMetaSearch": false,
                    "includeNullMetadata": true,
                    "legendFormat": "__auto",
                    "range": true,
                    "refId": "A",
                    "useBackend": false
                }
            ],
            "title": "Validator Block Height",
            "type": "stat"
        },
        {
            "datasource": {
                "type": "prometheus",
                "uid": "${DS_PROMETHEUS}"
            },
            "fieldConfig": {
                "defaults": {
                    "color": {
                        "mode": "thresholds"
                    },
                    "mappings": [
                        {
                            "options": {
                                "0": {
                                    "color": "red",
                                    "index": 0,
                                    "text": "No"
                                }
                            },
                            "type": "value"
                        },
                        {
                            "options": {
                                "from": 1,
                                "result": {
                                    "color": "green",
                                    "index": 1,
                                    "text": "Yes"
                                },
                                "to": 1000000
                            },
                            "type": "range"
                        }
                    ],
                    "thresholds": {
                        "mode": "absolute",
                        "steps": [
                            {
                                "color": "green",
                                "value": null
                            }
                        ]
                    }
                },
                "overrides": []
            },
            "gridPos": {
                "h": 4,
                "w": 3,
                "x": 0,
                "y": 14
            },
            "id": 37,
            "options": {
                "colorMode": "background",
                "graphMode": "area",
                "justifyMode": "auto",
                "orientation": "auto",
                "reduceOptions": {
                    "calcs": [
                        "lastNotNull"
                    ],
                    "fields": "",
                    "values": false
                },
                "showPercentChange": false,
                "textMode": "auto",
                "wideLayout": true
            },
            "pluginVersion": "10.4.2",
            "targets": [
                {
                    "datasource": {
                        "type": "prometheus",
                        "uid": "${DS_PROMETHEUS}"
                    },
                    "disableTextWrap": false,
                    "editorMode": "code",
                    "exemplar": false,
                    "expr": "increase(snarkos_bft_height_total{role=\"client\",chain=\"$chain\"}[5m]) > bool 1",
                    "format": "time_series",
                    "fullMetaSearch": false,
                    "includeNullMetadata": true,
                    "instant": false,
                    "legendFormat": "",
                    "range": true,
                    "refId": "A",
                    "useBackend": false
                }
            ],
            "title": "Client Height Increasing?",
            "type": "stat"
        },
        {
            "datasource": {
                "type": "prometheus",
                "uid": "${DS_PROMETHEUS}"
            },
            "fieldConfig": {
                "defaults": {
                    "color": {
                        "mode": "thresholds"
                    },
                    "mappings": [],
                    "thresholds": {
                        "mode": "absolute",
                        "steps": [
                            {
                                "color": "green",
                                "value": null
                            }
                        ]
                    }
                },
                "overrides": []
            },
            "gridPos": {
                "h": 4,
                "w": 8,
                "x": 3,
                "y": 14
            },
            "id": 2,
            "options": {
                "colorMode": "value",
                "graphMode": "area",
                "justifyMode": "auto",
                "orientation": "auto",
                "reduceOptions": {
                    "calcs": [
                        "lastNotNull"
                    ],
                    "fields": "",
                    "values": false
                },
                "showPercentChange": false,
                "textMode": "auto",
                "wideLayout": true
            },
            "pluginVersion": "10.4.2",
            "targets": [
                {
                    "datasource": {
                        "type": "prometheus",
                        "uid": "${DS_PROMETHEUS}"
                    },
                    "disableTextWrap": false,
                    "editorMode": "code",
                    "expr": "snarkos_bft_height_total{role=\"client\",chain=\"$chain\"}",
                    "fullMetaSearch": false,
                    "includeNullMetadata": true,
                    "legendFormat": "__auto",
                    "range": true,
                    "refId": "A",
                    "useBackend": false
                }
            ],
            "title": "Client Block Heights",
            "type": "stat"
        },
        {
            "collapsed": false,
            "gridPos": {
                "h": 1,
                "w": 24,
                "x": 0,
                "y": 18
            },
            "id": 20,
            "panels": [],
            "title": "Chain Health",
            "type": "row"
        },
        {
            "datasource": {
                "type": "prometheus",
                "uid": "${DS_PROMETHEUS}"
            },
            "description": "",
            "fieldConfig": {
                "defaults": {
                    "color": {
                        "mode": "palette-classic"
                    },
                    "custom": {
                        "axisBorderShow": false,
                        "axisCenteredZero": false,
                        "axisColorMode": "text",
                        "axisLabel": "",
                        "axisPlacement": "auto",
                        "barAlignment": 0,
                        "drawStyle": "line",
                        "fillOpacity": 33,
                        "gradientMode": "opacity",
                        "hideFrom": {
                            "legend": false,
                            "tooltip": false,
                            "viz": false
                        },
                        "insertNulls": false,
                        "lineInterpolation": "linear",
                        "lineStyle": {
                            "fill": "solid"
                        },
                        "lineWidth": 1,
                        "pointSize": 5,
                        "scaleDistribution": {
                            "type": "linear"
                        },
                        "showPoints": "never",
                        "spanNulls": false,
                        "stacking": {
                            "group": "A",
                            "mode": "none"
                        },
                        "thresholdsStyle": {
                            "mode": "off"
                        }
                    },
                    "decimals": 2,
                    "mappings": [],
                    "min": 0,
                    "thresholds": {
                        "mode": "absolute",
                        "steps": [
                            {
                                "color": "green",
                                "value": null
                            }
                        ]
                    },
                    "unit": "short"
                },
                "overrides": [
                    {
                        "matcher": {
                            "id": "byName",
                            "options": "Block Time - 24h average"
                        },
                        "properties": [
                            {
                                "id": "custom.fillOpacity",
                                "value": 0
                            },
                            {
                                "id": "custom.lineWidth",
                                "value": 2
                            }
                        ]
                    },
                    {
                        "matcher": {
                            "id": "byName",
                            "options": "Block Time - 6h average"
                        },
                        "properties": [
                            {
                                "id": "custom.fillOpacity",
                                "value": 0
                            },
                            {
                                "id": "custom.lineWidth",
                                "value": 2
                            }
                        ]
                    },
                    {
                        "matcher": {
                            "id": "byName",
                            "options": "Blocks Produced"
                        },
                        "properties": [
                            {
                                "id": "custom.drawStyle",
                                "value": "bars"
                            },
                            {
                                "id": "custom.fillOpacity",
                                "value": 90
                            },
                            {
                                "id": "custom.lineWidth",
                                "value": 0
                            },
                            {
                                "id": "custom.axisPlacement",
                                "value": "hidden"
                            },
                            {
                                "id": "color",
                                "value": {
                                    "fixedColor": "blue",
                                    "mode": "fixed"
                                }
                            },
                            {
                                "id": "custom.hideFrom",
                                "value": {
                                    "legend": true,
                                    "tooltip": true,
                                    "viz": false
                                }
                            }
                        ]
                    }
                ]
            },
            "gridPos": {
                "h": 10,
                "w": 12,
                "x": 0,
                "y": 19
            },
            "id": 41,
            "options": {
                "legend": {
                    "calcs": [
                        "min",
                        "max",
                        "mean",
                        "sum"
                    ],
                    "displayMode": "table",
                    "placement": "bottom",
                    "showLegend": true,
                    "sortBy": "Max",
                    "sortDesc": true
                },
                "tooltip": {
                    "mode": "multi",
                    "sort": "none"
                }
            },
            "pluginVersion": "8.3.3",
            "targets": [
                {
                    "datasource": {
                        "type": "prometheus",
                        "uid": "${DS_PROMETHEUS}"
                    },
                    "editorMode": "code",
                    "exemplar": true,
                    "expr": "1 / avg(rate(snarkos_bft_height_total{chain=\"$chain\"}[15m]))",
                    "interval": "",
                    "legendFormat": "Block Time - 15min average",
                    "range": true,
                    "refId": "A"
                },
                {
                    "datasource": {
                        "type": "prometheus",
                        "uid": "${DS_PROMETHEUS}"
                    },
                    "editorMode": "code",
                    "exemplar": true,
                    "expr": "1 / avg(rate(snarkos_bft_height_total{chain=\"$chain\"}[6h]))",
                    "hide": false,
                    "interval": "",
                    "legendFormat": "Block Time - 6h average",
                    "range": true,
                    "refId": "B"
                },
                {
                    "datasource": {
                        "type": "prometheus",
                        "uid": "${DS_PROMETHEUS}"
                    },
                    "editorMode": "code",
                    "exemplar": true,
                    "expr": "1 / avg(rate(snarkos_bft_height_total{chain=\"$chain\"}[1d])) ",
                    "hide": false,
                    "interval": "",
                    "legendFormat": "Block Time - 24h average",
                    "range": true,
                    "refId": "C"
                },
                {
                    "datasource": {
                        "type": "prometheus",
                        "uid": "${DS_PROMETHEUS}"
                    },
                    "editorMode": "code",
                    "expr": "1 / avg(increase(snarkos_bft_height_total{chain=\"$chain\"}[45s]))",
                    "hide": false,
                    "interval": "",
                    "legendFormat": "Blocks Produced",
                    "range": true,
                    "refId": "E"
                }
            ],
            "title": "Block Speed (seconds)",
            "type": "timeseries"
        },
        {
            "datasource": {
                "type": "prometheus",
                "uid": "${DS_PROMETHEUS}"
            },
            "description": "",
            "fieldConfig": {
                "defaults": {
                    "color": {
                        "mode": "palette-classic"
                    },
                    "custom": {
                        "axisBorderShow": false,
                        "axisCenteredZero": false,
                        "axisColorMode": "text",
                        "axisLabel": "",
                        "axisPlacement": "auto",
                        "barAlignment": 0,
                        "drawStyle": "line",
                        "fillOpacity": 33,
                        "gradientMode": "opacity",
                        "hideFrom": {
                            "legend": false,
                            "tooltip": false,
                            "viz": false
                        },
                        "insertNulls": false,
                        "lineInterpolation": "linear",
                        "lineStyle": {
                            "fill": "solid"
                        },
                        "lineWidth": 1,
                        "pointSize": 5,
                        "scaleDistribution": {
                            "type": "linear"
                        },
                        "showPoints": "never",
                        "spanNulls": false,
                        "stacking": {
                            "group": "A",
                            "mode": "none"
                        },
                        "thresholdsStyle": {
                            "mode": "off"
                        }
                    },
                    "decimals": 2,
                    "mappings": [],
                    "min": 0,
                    "thresholds": {
                        "mode": "absolute",
                        "steps": [
                            {
                                "color": "green",
                                "value": null
                            }
                        ]
                    },
                    "unit": "short"
                },
                "overrides": [
                    {
                        "matcher": {
                            "id": "byName",
                            "options": "Proposal Round - 24h average"
                        },
                        "properties": [
                            {
                                "id": "custom.fillOpacity",
                                "value": 0
                            },
                            {
                                "id": "custom.lineWidth",
                                "value": 2
                            }
                        ]
                    },
                    {
                        "matcher": {
                            "id": "byName",
                            "options": "Proposal Round - 6h average"
                        },
                        "properties": [
                            {
                                "id": "custom.fillOpacity",
                                "value": 0
                            },
                            {
                                "id": "custom.lineWidth",
                                "value": 2
                            }
                        ]
                    },
                    {
                        "matcher": {
                            "id": "byName",
                            "options": "Proposals Produced"
                        },
                        "properties": [
                            {
                                "id": "custom.drawStyle",
                                "value": "bars"
                            },
                            {
                                "id": "custom.fillOpacity",
                                "value": 90
                            },
                            {
                                "id": "custom.lineWidth",
                                "value": 0
                            },
                            {
                                "id": "custom.axisPlacement",
                                "value": "hidden"
                            },
                            {
                                "id": "color",
                                "value": {
                                    "fixedColor": "blue",
                                    "mode": "fixed"
                                }
                            },
                            {
                                "id": "custom.hideFrom",
                                "value": {
                                    "legend": true,
                                    "tooltip": true,
                                    "viz": false
                                }
                            }
                        ]
                    }
                ]
            },
            "gridPos": {
                "h": 10,
                "w": 12,
                "x": 12,
                "y": 19
            },
            "id": 42,
            "options": {
                "legend": {
                    "calcs": [
                        "min",
                        "max",
                        "mean",
                        "sum"
                    ],
                    "displayMode": "table",
                    "placement": "bottom",
                    "showLegend": true,
                    "sortBy": "Max",
                    "sortDesc": true
                },
                "tooltip": {
                    "mode": "multi",
                    "sort": "none"
                }
            },
            "pluginVersion": "8.3.3",
            "targets": [
                {
                    "datasource": {
                        "type": "prometheus",
                        "uid": "${DS_PROMETHEUS}"
                    },
                    "editorMode": "code",
                    "exemplar": true,
                    "expr": "1 / avg(rate(snarkos_bft_primary_proposal_round{chain=\"$chain\"}[15m]))",
                    "interval": "",
                    "legendFormat": "Proposal Round - 15min average",
                    "range": true,
                    "refId": "A"
                },
                {
                    "datasource": {
                        "type": "prometheus",
                        "uid": "${DS_PROMETHEUS}"
                    },
                    "editorMode": "code",
                    "exemplar": true,
                    "expr": "1 / avg(rate(snarkos_bft_primary_proposal_round{chain=\"$chain\"}[6h]))",
                    "hide": false,
                    "interval": "",
                    "legendFormat": "Proposal Round - 6h average",
                    "range": true,
                    "refId": "B"
                },
                {
                    "datasource": {
                        "type": "prometheus",
                        "uid": "${DS_PROMETHEUS}"
                    },
                    "editorMode": "code",
                    "exemplar": true,
                    "expr": "1 / avg(rate(snarkos_bft_primary_proposal_round{chain=\"$chain\"}[1d])) ",
                    "hide": false,
                    "interval": "",
                    "legendFormat": "Proposal Round - 24h average",
                    "range": true,
                    "refId": "C"
                },
                {
                    "datasource": {
                        "type": "prometheus",
                        "uid": "${DS_PROMETHEUS}"
                    },
                    "editorMode": "code",
                    "expr": "1 / avg(increase(snarkos_bft_primary_proposal_round{chain=\"$chain\"}[45s]))",
                    "hide": false,
                    "interval": "",
                    "legendFormat": "Proposals Produced",
                    "range": true,
                    "refId": "E"
                }
            ],
            "title": "Proposal Rounds (seconds)",
            "type": "timeseries"
        },
        {
            "datasource": {
                "type": "prometheus",
                "uid": "${DS_PROMETHEUS}"
            },
            "description": "",
            "fieldConfig": {
                "defaults": {
                    "color": {
                        "mode": "palette-classic"
                    },
                    "custom": {
                        "axisBorderShow": false,
                        "axisCenteredZero": false,
                        "axisColorMode": "text",
                        "axisLabel": "",
                        "axisPlacement": "auto",
                        "barAlignment": 0,
                        "drawStyle": "line",
                        "fillOpacity": 33,
                        "gradientMode": "opacity",
                        "hideFrom": {
                            "legend": false,
                            "tooltip": false,
                            "viz": false
                        },
                        "insertNulls": false,
                        "lineInterpolation": "linear",
                        "lineStyle": {
                            "fill": "solid"
                        },
                        "lineWidth": 1,
                        "pointSize": 5,
                        "scaleDistribution": {
                            "type": "linear"
                        },
                        "showPoints": "never",
                        "spanNulls": false,
                        "stacking": {
                            "group": "A",
                            "mode": "none"
                        },
                        "thresholdsStyle": {
                            "mode": "off"
                        }
                    },
                    "decimals": 2,
                    "mappings": [],
                    "min": 0,
                    "thresholds": {
                        "mode": "absolute",
                        "steps": [
                            {
                                "color": "green",
                                "value": null
                            }
                        ]
                    },
                    "unit": "short"
                },
                "overrides": [
                    {
                        "matcher": {
                            "id": "byName",
                            "options": "Mempool Size / min"
                        },
                        "properties": [
                            {
                                "id": "custom.fillOpacity",
                                "value": 0
                            },
                            {
                                "id": "custom.lineWidth",
                                "value": 2
                            }
                        ]
                    },
                    {
                        "matcher": {
                            "id": "byName",
                            "options": "Successful Tx / min"
                        },
                        "properties": [
                            {
                                "id": "custom.fillOpacity",
                                "value": 0
                            },
                            {
                                "id": "custom.lineWidth",
                                "value": 2
                            }
                        ]
                    }
                ]
            },
            "gridPos": {
                "h": 10,
                "w": 12,
                "x": 0,
                "y": 29
            },
            "id": 38,
            "options": {
                "legend": {
                    "calcs": [
                        "min",
                        "max",
                        "mean",
                        "sum"
                    ],
                    "displayMode": "table",
                    "placement": "bottom",
                    "showLegend": true,
                    "sortBy": "Max",
                    "sortDesc": true
                },
                "tooltip": {
                    "mode": "multi",
                    "sort": "none"
                }
            },
            "pluginVersion": "8.3.3",
            "targets": [
                {
                    "datasource": {
                        "type": "prometheus",
                        "uid": "${DS_PROMETHEUS}"
                    },
                    "editorMode": "code",
                    "exemplar": true,
                    "expr": "avg(rate(snarkos_blocks_transactions_total{role=\"validator\",chain=\"$chain\"}[6h])) * 60",
                    "hide": false,
                    "interval": "",
                    "legendFormat": "Successful Tx / min",
                    "range": true,
                    "refId": "B"
                },
                {
                    "datasource": {
                        "type": "prometheus",
                        "uid": "${DS_PROMETHEUS}"
                    },
                    "editorMode": "code",
                    "expr": "avg(rate(snarkos_consensus_unconfirmed_transactions_total{role=\"validator\",chain=\"$chain\"}[6h])) * 60",
                    "hide": false,
                    "interval": "",
                    "legendFormat": "Failed Tx / min",
                    "range": true,
                    "refId": "E"
                },
                {
                    "datasource": {
                        "type": "prometheus",
                        "uid": "${DS_PROMETHEUS}"
                    },
                    "editorMode": "code",
                    "expr": "avg(rate(snarkos_blocks_aborted_transactions{role=\"validator\",chain=\"$chain\"}[6h])) * 60",
                    "hide": false,
                    "instant": false,
                    "legendFormat": "Aborted Tx / min",
                    "range": true,
                    "refId": "A"
                }
            ],
            "title": "6h Txs Overview / min",
            "type": "timeseries"
        },
        {
            "datasource": {
                "type": "prometheus",
                "uid": "${DS_PROMETHEUS}"
            },
            "description": "",
            "fieldConfig": {
                "defaults": {
                    "color": {
                        "mode": "palette-classic"
                    },
                    "custom": {
                        "axisBorderShow": false,
                        "axisCenteredZero": false,
                        "axisColorMode": "text",
                        "axisLabel": "",
                        "axisPlacement": "auto",
                        "barAlignment": 0,
                        "drawStyle": "line",
                        "fillOpacity": 33,
                        "gradientMode": "opacity",
                        "hideFrom": {
                            "legend": false,
                            "tooltip": false,
                            "viz": false
                        },
                        "insertNulls": false,
                        "lineInterpolation": "linear",
                        "lineStyle": {
                            "fill": "solid"
                        },
                        "lineWidth": 1,
                        "pointSize": 5,
                        "scaleDistribution": {
                            "type": "linear"
                        },
                        "showPoints": "never",
                        "spanNulls": false,
                        "stacking": {
                            "group": "A",
                            "mode": "none"
                        },
                        "thresholdsStyle": {
                            "mode": "off"
                        }
                    },
                    "decimals": 2,
                    "mappings": [],
                    "min": 0,
                    "thresholds": {
                        "mode": "absolute",
                        "steps": [
                            {
                                "color": "green",
                                "value": null
                            }
                        ]
                    },
                    "unit": "short"
                },
                "overrides": [
                    {
                        "matcher": {
                            "id": "byName",
                            "options": "Block Solutions / min"
                        },
                        "properties": [
                            {
                                "id": "custom.fillOpacity",
                                "value": 0
                            },
                            {
                                "id": "custom.lineWidth",
                                "value": 2
                            }
                        ]
                    },
                    {
                        "matcher": {
                            "id": "byName",
                            "options": "Failed Solutions / min"
                        },
                        "properties": [
                            {
                                "id": "custom.fillOpacity",
                                "value": 0
                            },
                            {
                                "id": "custom.lineWidth",
                                "value": 2
                            }
                        ]
                    }
                ]
            },
            "gridPos": {
                "h": 10,
                "w": 12,
                "x": 12,
                "y": 29
            },
            "id": 39,
            "options": {
                "legend": {
                    "calcs": [
                        "min",
                        "max",
                        "mean",
                        "sum"
                    ],
                    "displayMode": "table",
                    "placement": "bottom",
                    "showLegend": true,
                    "sortBy": "Max",
                    "sortDesc": true
                },
                "tooltip": {
                    "mode": "multi",
                    "sort": "none"
                }
            },
            "pluginVersion": "8.3.3",
            "targets": [
                {
                    "datasource": {
                        "type": "prometheus",
                        "uid": "${DS_PROMETHEUS}"
                    },
                    "editorMode": "code",
                    "exemplar": true,
                    "expr": "avg(rate(snarkos_blocks_solutions_total{role=\"validator\",chain=\"$chain\"}[6h])) * 60",
                    "hide": false,
                    "interval": "",
                    "legendFormat": "Block Solutions / min",
                    "range": true,
                    "refId": "B"
                },
                {
                    "datasource": {
                        "type": "prometheus",
                        "uid": "${DS_PROMETHEUS}"
                    },
                    "editorMode": "code",
                    "expr": "avg(rate(snarkos_consensus_unconfirmed_solutions_total{role=\"validator\",chain=\"$chain\"}[6h])) * 60",
                    "hide": false,
                    "interval": "",
                    "legendFormat": "Failed Solutions / min",
                    "range": true,
                    "refId": "E"
                },
                {
                    "datasource": {
                        "type": "prometheus",
                        "uid": "${DS_PROMETHEUS}"
                    },
                    "editorMode": "code",
                    "expr": "avg(rate(snarkos_blocks_aborted_solutions{role=\"validator\",chain=\"$chain\"}[6h])) * 60",
                    "hide": false,
                    "instant": false,
                    "legendFormat": "Aborted Solutions / min",
                    "range": true,
                    "refId": "A"
                }
            ],
            "title": "6h Block Solution Overview / min",
            "type": "timeseries"
        },
        {
            "datasource": {
                "type": "prometheus",
                "uid": "${DS_PROMETHEUS}"
            },
            "fieldConfig": {
                "defaults": {
                    "color": {
                        "mode": "palette-classic"
                    },
                    "custom": {
                        "axisBorderShow": false,
                        "axisCenteredZero": false,
                        "axisColorMode": "text",
                        "axisLabel": "",
                        "axisPlacement": "auto",
                        "barAlignment": 0,
                        "drawStyle": "line",
                        "fillOpacity": 0,
                        "gradientMode": "none",
                        "hideFrom": {
                            "legend": false,
                            "tooltip": false,
                            "viz": false
                        },
                        "insertNulls": false,
                        "lineInterpolation": "linear",
                        "lineWidth": 1,
                        "pointSize": 5,
                        "scaleDistribution": {
                            "type": "linear"
                        },
                        "showPoints": "auto",
                        "spanNulls": false,
                        "stacking": {
                            "group": "A",
                            "mode": "none"
                        },
                        "thresholdsStyle": {
                            "mode": "off"
                        }
                    },
                    "mappings": [],
                    "thresholds": {
                        "mode": "absolute",
                        "steps": [
                            {
                                "color": "green",
                                "value": null
                            },
                            {
                                "color": "red",
                                "value": 80
                            }
                        ]
                    }
                },
                "overrides": []
            },
            "gridPos": {
                "h": 6,
                "w": 8,
                "x": 0,
                "y": 39
            },
            "id": 18,
            "options": {
                "legend": {
                    "calcs": [],
                    "displayMode": "list",
                    "placement": "bottom",
                    "showLegend": true
                },
                "tooltip": {
                    "mode": "single",
                    "sort": "none"
                }
            },
            "targets": [
                {
                    "datasource": {
                        "type": "prometheus",
                        "uid": "${DS_PROMETHEUS}"
                    },
                    "disableTextWrap": false,
                    "editorMode": "code",
                    "expr": "snarkos_router_restricted_total{chain=\"$chain\"}",
                    "fullMetaSearch": false,
                    "includeNullMetadata": true,
                    "instant": false,
                    "legendFormat": "{{role}}",
                    "range": true,
                    "refId": "A",
                    "useBackend": false
                }
            ],
            "title": "Restricted Peers",
            "type": "timeseries"
        },
        {
            "datasource": {
                "type": "prometheus",
                "uid": "${DS_PROMETHEUS}"
            },
            "fieldConfig": {
                "defaults": {
                    "color": {
                        "mode": "palette-classic"
                    },
                    "custom": {
                        "axisBorderShow": false,
                        "axisCenteredZero": false,
                        "axisColorMode": "text",
                        "axisLabel": "",
                        "axisPlacement": "auto",
                        "barAlignment": 0,
                        "drawStyle": "line",
                        "fillOpacity": 0,
                        "gradientMode": "none",
                        "hideFrom": {
                            "legend": false,
                            "tooltip": false,
                            "viz": false
                        },
                        "insertNulls": false,
                        "lineInterpolation": "linear",
                        "lineWidth": 1,
                        "pointSize": 5,
                        "scaleDistribution": {
                            "type": "linear"
                        },
                        "showPoints": "auto",
                        "spanNulls": false,
                        "stacking": {
                            "group": "A",
                            "mode": "none"
                        },
                        "thresholdsStyle": {
                            "mode": "off"
                        }
                    },
                    "mappings": [],
                    "thresholds": {
                        "mode": "absolute",
                        "steps": [
                            {
                                "color": "green",
                                "value": null
                            },
                            {
                                "color": "red",
                                "value": 80
                            }
                        ]
                    }
                },
                "overrides": []
            },
            "gridPos": {
                "h": 12,
                "w": 16,
                "x": 8,
                "y": 39
            },
            "id": 17,
            "options": {
                "legend": {
                    "calcs": [],
                    "displayMode": "list",
                    "placement": "bottom",
                    "showLegend": true
                },
                "tooltip": {
                    "mode": "single",
                    "sort": "none"
                }
            },
            "targets": [
                {
                    "datasource": {
                        "type": "prometheus",
                        "uid": "${DS_PROMETHEUS}"
                    },
                    "disableTextWrap": false,
                    "editorMode": "builder",
                    "expr": "snarkos_router_connected_total{chain=\"$chain\"}",
                    "fullMetaSearch": false,
                    "includeNullMetadata": true,
                    "instant": false,
                    "legendFormat": "{{role}}",
                    "range": true,
                    "refId": "A",
                    "useBackend": false
                }
            ],
            "title": "Connected Peers",
            "type": "timeseries"
        },
        {
            "datasource": {
                "type": "prometheus",
                "uid": "${DS_PROMETHEUS}"
            },
            "fieldConfig": {
                "defaults": {
                    "color": {
                        "mode": "palette-classic"
                    },
                    "custom": {
                        "axisBorderShow": false,
                        "axisCenteredZero": false,
                        "axisColorMode": "text",
                        "axisLabel": "",
                        "axisPlacement": "auto",
                        "barAlignment": 0,
                        "drawStyle": "line",
                        "fillOpacity": 0,
                        "gradientMode": "none",
                        "hideFrom": {
                            "legend": false,
                            "tooltip": false,
                            "viz": false
                        },
                        "insertNulls": false,
                        "lineInterpolation": "linear",
                        "lineWidth": 1,
                        "pointSize": 5,
                        "scaleDistribution": {
                            "type": "linear"
                        },
                        "showPoints": "auto",
                        "spanNulls": false,
                        "stacking": {
                            "group": "A",
                            "mode": "none"
                        },
                        "thresholdsStyle": {
                            "mode": "off"
                        }
                    },
                    "displayName": "Queue Depth",
                    "mappings": [],
                    "thresholds": {
                        "mode": "absolute",
                        "steps": [
                            {
                                "color": "green",
                                "value": null
                            },
                            {
                                "color": "red",
                                "value": 80
                            }
                        ]
                    }
                },
                "overrides": []
            },
            "gridPos": {
                "h": 6,
                "w": 8,
                "x": 0,
                "y": 45
            },
            "id": 31,
            "options": {
                "legend": {
                    "calcs": [],
                    "displayMode": "list",
                    "placement": "bottom",
                    "showLegend": true
                },
                "tooltip": {
                    "mode": "single",
                    "sort": "none"
                }
            },
            "targets": [
                {
                    "datasource": {
                        "type": "prometheus",
                        "uid": "${DS_PROMETHEUS}"
                    },
                    "disableTextWrap": false,
                    "editorMode": "builder",
                    "expr": "snarkos_tcp_tasks_total{chain=\"$chain\"}",
                    "fullMetaSearch": false,
                    "includeNullMetadata": true,
                    "instant": false,
                    "legendFormat": "{{role}}",
                    "range": true,
                    "refId": "A",
                    "useBackend": false
                }
            ],
            "title": "TCP Queue Depth",
            "type": "timeseries"
        },
        {
            "datasource": {
                "type": "prometheus",
                "uid": "${DS_PROMETHEUS}"
            },
            "fieldConfig": {
                "defaults": {
                    "color": {
                        "mode": "palette-classic"
                    },
                    "custom": {
                        "axisBorderShow": false,
                        "axisCenteredZero": false,
                        "axisColorMode": "text",
                        "axisLabel": "",
                        "axisPlacement": "auto",
                        "barAlignment": 0,
                        "drawStyle": "line",
                        "fillOpacity": 0,
                        "gradientMode": "none",
                        "hideFrom": {
                            "legend": false,
                            "tooltip": false,
                            "viz": false
                        },
                        "insertNulls": false,
                        "lineInterpolation": "linear",
                        "lineWidth": 1,
                        "pointSize": 5,
                        "scaleDistribution": {
                            "type": "linear"
                        },
                        "showPoints": "auto",
                        "spanNulls": false,
                        "stacking": {
                            "group": "A",
                            "mode": "none"
                        },
                        "thresholdsStyle": {
                            "mode": "off"
                        }
                    },
                    "mappings": [],
                    "thresholds": {
                        "mode": "absolute",
                        "steps": [
                            {
                                "color": "green",
                                "value": null
                            },
                            {
                                "color": "red",
                                "value": 80
                            }
                        ]
                    }
                },
                "overrides": []
            },
            "gridPos": {
                "h": 6,
                "w": 8,
                "x": 0,
                "y": 51
            },
            "id": 16,
            "options": {
                "legend": {
                    "calcs": [],
                    "displayMode": "list",
                    "placement": "bottom",
                    "showLegend": true
                },
                "tooltip": {
                    "mode": "single",
                    "sort": "none"
                }
            },
            "targets": [
                {
                    "datasource": {
                        "type": "prometheus",
                        "uid": "${DS_PROMETHEUS}"
                    },
                    "disableTextWrap": false,
                    "editorMode": "code",
                    "expr": "snarkos_router_candidate_total{chain=\"$chain\"}",
                    "fullMetaSearch": false,
                    "includeNullMetadata": true,
                    "instant": false,
                    "legendFormat": "{{role}}",
                    "range": true,
                    "refId": "A",
                    "useBackend": false
                }
            ],
            "title": "Total Clients",
            "type": "timeseries"
        },
        {
            "collapsed": true,
            "gridPos": {
                "h": 1,
                "w": 24,
                "x": 0,
                "y": 57
            },
            "id": 27,
            "panels": [
                {
                    "datasource": {
                        "type": "prometheus",
                        "uid": "${DS_PROMETHEUS}"
                    },
                    "fieldConfig": {
                        "defaults": {
                            "color": {
                                "mode": "palette-classic"
                            },
                            "custom": {
                                "axisBorderShow": false,
                                "axisCenteredZero": false,
                                "axisColorMode": "text",
                                "axisLabel": "",
                                "axisPlacement": "auto",
                                "barAlignment": 0,
                                "drawStyle": "line",
                                "fillOpacity": 0,
                                "gradientMode": "none",
                                "hideFrom": {
                                    "legend": false,
                                    "tooltip": false,
                                    "viz": false
                                },
                                "insertNulls": false,
                                "lineInterpolation": "linear",
                                "lineWidth": 1,
                                "pointSize": 5,
                                "scaleDistribution": {
                                    "type": "linear"
                                },
                                "showPoints": "auto",
                                "spanNulls": false,
                                "stacking": {
                                    "group": "A",
                                    "mode": "none"
                                },
                                "thresholdsStyle": {
                                    "mode": "off"
                                }
                            },
                            "displayName": "Average Certificate Commit Latency",
                            "mappings": [],
                            "thresholds": {
                                "mode": "absolute",
                                "steps": [
                                    {
                                        "color": "green",
                                        "value": null
                                    },
                                    {
                                        "color": "red",
                                        "value": 80
                                    }
                                ]
                            },
                            "unit": "s"
                        },
                        "overrides": []
                    },
                    "gridPos": {
                        "h": 8,
                        "w": 8,
                        "x": 0,
                        "y": 23
                    },
                    "id": 28,
                    "options": {
                        "legend": {
                            "calcs": [],
                            "displayMode": "list",
                            "placement": "bottom",
                            "showLegend": true
                        },
                        "tooltip": {
                            "mode": "single",
                            "sort": "none"
                        }
                    },
                    "pluginVersion": "9.4.1",
                    "targets": [
                        {
                            "datasource": {
                                "type": "prometheus",
                                "uid": "${DS_PROMETHEUS}"
                            },
                            "disableTextWrap": false,
                            "editorMode": "code",
                            "exemplar": false,
                            "expr": "avg(snarkos_consensus_certificate_commit_latency_secs{chain=\"$chain\"})",
                            "format": "time_series",
                            "fullMetaSearch": false,
                            "includeNullMetadata": true,
                            "instant": false,
                            "legendFormat": "__auto",
                            "range": true,
                            "refId": "A",
                            "useBackend": false
                        }
                    ],
                    "title": "Certificate Commit Latency",
                    "transformations": [
                        {
                            "id": "filterByValue",
                            "options": {
                                "filters": [
                                    {
                                        "config": {
                                            "id": "equal",
                                            "options": {
                                                "value": ""
                                            }
                                        },
                                        "fieldName": "certificate_round"
                                    }
                                ],
                                "match": "all",
                                "type": "exclude"
                            }
                        }
                    ],
                    "type": "timeseries"
                },
                {
                    "datasource": {
                        "type": "prometheus",
                        "uid": "${DS_PROMETHEUS}"
                    },
                    "fieldConfig": {
                        "defaults": {
                            "color": {
                                "mode": "palette-classic"
                            },
                            "custom": {
                                "axisBorderShow": false,
                                "axisCenteredZero": false,
                                "axisColorMode": "text",
                                "axisLabel": "",
                                "axisPlacement": "auto",
                                "barAlignment": 0,
                                "drawStyle": "line",
                                "fillOpacity": 0,
                                "gradientMode": "none",
                                "hideFrom": {
                                    "legend": false,
                                    "tooltip": false,
                                    "viz": false
                                },
                                "insertNulls": false,
                                "lineInterpolation": "linear",
                                "lineWidth": 1,
                                "pointSize": 5,
                                "scaleDistribution": {
                                    "type": "linear"
                                },
                                "showPoints": "auto",
                                "spanNulls": false,
                                "stacking": {
                                    "group": "A",
                                    "mode": "none"
                                },
                                "thresholdsStyle": {
                                    "mode": "off"
                                }
                            },
                            "displayName": "Average round latency",
                            "mappings": [],
                            "thresholds": {
                                "mode": "absolute",
                                "steps": [
                                    {
                                        "color": "green",
                                        "value": null
                                    },
                                    {
                                        "color": "red",
                                        "value": 15
                                    }
                                ]
                            },
                            "unit": "s"
                        },
                        "overrides": []
                    },
                    "gridPos": {
                        "h": 8,
                        "w": 9,
                        "x": 8,
                        "y": 23
                    },
                    "id": 29,
                    "options": {
                        "legend": {
                            "calcs": [],
                            "displayMode": "list",
                            "placement": "bottom",
                            "showLegend": true
                        },
                        "tooltip": {
                            "mode": "single",
                            "sort": "none"
                        }
                    },
                    "targets": [
                        {
                            "datasource": {
                                "type": "prometheus",
                                "uid": "${DS_PROMETHEUS}"
                            },
                            "disableTextWrap": false,
                            "editorMode": "code",
                            "exemplar": false,
                            "expr": "avg(snarkos_bft_commit_rounds_latency_secs{chain=\"$chain\"})",
                            "format": "time_series",
                            "fullMetaSearch": false,
                            "includeNullMetadata": true,
                            "legendFormat": "__auto",
                            "range": true,
                            "refId": "A",
                            "useBackend": false
                        }
                    ],
                    "title": "Commit Rounds Latency",
                    "type": "timeseries"
                },
                {
                    "datasource": {
                        "type": "prometheus",
                        "uid": "${DS_PROMETHEUS}"
                    },
                    "fieldConfig": {
                        "defaults": {
                            "color": {
                                "mode": "palette-classic"
                            },
                            "custom": {
                                "axisBorderShow": false,
                                "axisCenteredZero": false,
                                "axisColorMode": "text",
                                "axisLabel": "",
                                "axisPlacement": "auto",
                                "barAlignment": 0,
                                "drawStyle": "line",
                                "fillOpacity": 0,
                                "gradientMode": "none",
                                "hideFrom": {
                                    "legend": false,
                                    "tooltip": false,
                                    "viz": false
                                },
                                "insertNulls": false,
                                "lineInterpolation": "linear",
                                "lineWidth": 1,
                                "pointSize": 5,
                                "scaleDistribution": {
                                    "type": "linear"
                                },
                                "showPoints": "auto",
                                "spanNulls": false,
                                "stacking": {
                                    "group": "A",
                                    "mode": "none"
                                },
                                "thresholdsStyle": {
                                    "mode": "off"
                                }
                            },
                            "displayName": "Average Block Latency",
                            "mappings": [],
                            "thresholds": {
                                "mode": "absolute",
                                "steps": [
                                    {
                                        "color": "green",
                                        "value": null
                                    },
                                    {
                                        "color": "red",
                                        "value": 80
                                    }
                                ]
                            },
                            "unit": "s"
                        },
                        "overrides": []
                    },
                    "gridPos": {
                        "h": 8,
                        "w": 7,
                        "x": 17,
                        "y": 23
                    },
                    "id": 30,
                    "options": {
                        "legend": {
                            "calcs": [],
                            "displayMode": "list",
                            "placement": "bottom",
                            "showLegend": true
                        },
                        "tooltip": {
                            "mode": "single",
                            "sort": "none"
                        }
                    },
                    "targets": [
                        {
                            "datasource": {
                                "type": "prometheus",
                                "uid": "${DS_PROMETHEUS}"
                            },
                            "disableTextWrap": false,
                            "editorMode": "code",
                            "expr": "avg(snarkos_consensus_block_latency_secs{chain=\"$chain\"})",
                            "fullMetaSearch": false,
                            "includeNullMetadata": true,
                            "instant": false,
                            "legendFormat": "__auto",
                            "range": true,
                            "refId": "A",
                            "useBackend": false
                        }
                    ],
                    "title": "Block Latency",
                    "type": "timeseries"
                }
            ],
            "title": "Consensus",
            "type": "row"
        }
    ],
    "schemaVersion": 39,
    "tags": [
        "aleo"
    ],
    "templating": {
        "list": [
            {
                "current": {
                    "selected": false,
                    "text": "Prometheus",
                    "value": "PBFA97CFB590B2093"
                },
                "hide": 2,
                "includeAll": false,
                "multi": false,
                "name": "DS_PROMETHEUS",
                "options": [],
                "query": "prometheus",
                "refresh": 1,
                "regex": "",
                "skipUrlSync": false,
                "type": "datasource"
            },
            {
                "current": {
                    "selected": false,
                    "text": "Infinity",
                    "value": "PD0067CAD9A63E081"
                },
                "hide": 2,
                "includeAll": false,
                "multi": false,
                "name": "DS_INFINITY",
                "options": [],
                "query": "yesoreyeram-infinity-datasource",
                "refresh": 1,
                "regex": "",
                "skipUrlSync": false,
                "type": "datasource"
            },
            {
                "current": {},
                "datasource": {
                    "type": "prometheus",
                    "uid": "${DS_PROMETHEUS}"
                },
                "definition": "label_values(snarkos_bft_height_total,job)",
                "hide": 0,
                "includeAll": false,
                "multi": false,
                "name": "job",
                "options": [],
                "query": {
                    "qryType": 1,
                    "query": "label_values(snarkos_bft_height_total,job)",
                    "refId": "PrometheusVariableQueryEditor-VariableQuery"
                },
                "refresh": 1,
                "regex": "",
                "skipUrlSync": false,
                "sort": 0,
                "type": "query"
            },
            {
                "current": {},
                "datasource": {
                    "type": "prometheus",
                    "uid": "${DS_PROMETHEUS}"
                },
                "definition": "label_values(snarkos_bft_height_total{job=\"$job\"},chain)",
                "hide": 0,
                "includeAll": false,
                "multi": false,
                "name": "chain",
                "options": [],
                "query": {
                    "qryType": 1,
                    "query": "label_values(snarkos_bft_height_total{job=\"$job\"},chain)",
                    "refId": "PrometheusVariableQueryEditor-VariableQuery"
                },
                "refresh": 1,
                "regex": "",
                "skipUrlSync": false,
                "sort": 0,
                "type": "query"
            },
            {
                "current": {
                    "selected": false,
                    "text": "https://canarynet-aleo-api.lavenderfive.com:443/mainnet",
                    "value": "https://canarynet-aleo-api.lavenderfive.com:443/mainnet"
                },
                "description": "example: https://aleo.lavenderfive.com:443/mainnet",
                "hide": 0,
                "includeAll": false,
                "multi": false,
                "name": "api",
                "options": [
                    {
                        "selected": true,
                        "text": "https://canarynet-aleo-api.lavenderfive.com:443/mainnet",
                        "value": "https://canarynet-aleo-api.lavenderfive.com:443/mainnet"
                    }
                ],
                "query": "https://canarynet-aleo-api.lavenderfive.com:443/mainnet",
                "queryValue": "",
                "skipUrlSync": false,
                "type": "custom"
            }
        ]
    },
    "time": {
        "from": "now-6h",
        "to": "now"
    },
    "timepicker": {},
    "timezone": "",
    "title": "Aleo Validator",
    "uid": "uaCXuyDSk",
    "version": 34,
    "weekStart": ""
}